tensql-1.0.0.dist-info/METADATA
tensql-1.0.0.dist-info/RECORD
tensql-1.0.0.dist-info/WHEEL
tensql-1.0.0.dist-info/LICENSE
tensql-1.0.0.dist-info/top_level.txt
tensql/_version.py
tensql/_PyObjectHelper.abi3.so
tensql/Table.py
tensql/Column.py
tensql/PyObjectHelper.py
tensql/Types.py
tensql/__init__.py
tensql/PrimaryKey.py
tensql/_PyHashOCNT.cpython-39-x86_64-linux-gnu.so
tensql/util.py
tensql/Database.py
tensql/LAIR/InnerBroadcast.py
tensql/LAIR/ElementwiseAdd.py
tensql/LAIR/Visitor.py
tensql/LAIR/ElementwiseApply.py
tensql/LAIR/AntiMask.py
tensql/LAIR/DotVxM.py
tensql/LAIR/InnerBroadcastStencil.py
tensql/LAIR/PermuteIndices.py
tensql/LAIR/CastLike.py
tensql/LAIR/InnerBroadcastMask.py
tensql/LAIR/Cast.py
tensql/LAIR/Reduction.py
tensql/LAIR/DotMxV.py
tensql/LAIR/VectorToColumnMatrix.py
tensql/LAIR/VectorToDiagMatrix.py
tensql/LAIR/Optimizer.py
tensql/LAIR/Mask.py
tensql/LAIR/Tensor.py
tensql/LAIR/ElementwiseMultiply.py
tensql/LAIR/__init__.py
tensql/LAIR/PrimaryKey.py
tensql/LAIR/Output.py
tensql/LAIR/Promote.py
tensql/LAIR/Node.py
tensql/LAIR/VectorToRowMatrix.py
tensql/LAIR/DotMxM.py
tensql/LAIR/Pattern.py
tensql/LAIR/visitors/index_algebra.py
tensql/LAIR/visitors/ShapeVisitor.py
tensql/LAIR/visitors/ReverseIndexVisitor.py
tensql/LAIR/visitors/NodeReplacer.py
tensql/LAIR/visitors/__init__.py
tensql/LAIR/visitors/IndexVisitor.py
tensql/QIR/QirColumn.py
tensql/QIR/ABCExpression.py
tensql/QIR/BooleanColumn.py
tensql/QIR/InsertQuery.py
tensql/QIR/ArithmeticConstant.py
tensql/QIR/Table.py
tensql/QIR/Visitor.py
tensql/QIR/ABCNode.py
tensql/QIR/BooleanConstant.py
tensql/QIR/ReductionExpression.py
tensql/QIR/LAIRTranslator.py
tensql/QIR/From.py
tensql/QIR/Query.py
tensql/QIR/ABCTableSequence.py
tensql/QIR/Constant.py
tensql/QIR/__init__.py
tensql/QIR/Joiner.py
tensql/QIR/ArithmeticUnaryExpression.py
tensql/QIR/GroupBy.py
tensql/QIR/ABCArithmeticExpression.py
tensql/QIR/Join.py
tensql/QIR/ABCBooleanExpression.py
tensql/QIR/ArithmeticBinaryExpression.py
tensql/QIR/BinaryExpression.py
tensql/QIR/SelectQuery.py
tensql/QIR/ABCUnaryExpression.py
