Metadata-Version: 2.1
Name: tensql
Version: 1.0.0
Summary: TenSQL
Author: Jon Roose
Author-email: jproose@sandia.gov
Maintainer: Jon Roose
Maintainer-email: jproose@sandia.gov
License: BSD Clause 3
Keywords: sparse linear algebra tensor sql
Classifier: Programming Language :: Python :: 3
Requires-Python: <3.10,>=3.9
License-File: LICENSE
Requires-Dist: pygraphblas
Requires-Dist: h5py
Requires-Dist: cython
Requires-Dist: wheel
Requires-Dist: numpy
Provides-Extra: benchmark
Requires-Dist: sqlalchemy ; extra == 'benchmark'
Requires-Dist: psycopg2 ; extra == 'benchmark'
Requires-Dist: pandasql ; extra == 'benchmark'
Provides-Extra: test
Requires-Dist: coverage ; extra == 'test'
Requires-Dist: psutil ; extra == 'test'
